fusion_threed/__init__.py
fusion_threed/model.py
fusion_threed-0.0.1.dist-info/LICENSE
fusion_threed-0.0.1.dist-info/METADATA
fusion_threed-0.0.1.dist-info/WHEEL
fusion_threed-0.0.1.dist-info/RECORD
